README.md
setup.py
libplot/__init__.py
libplot/libplot.py
libplot.egg-info/PKG-INFO
libplot.egg-info/SOURCES.txt
libplot.egg-info/dependency_links.txt
libplot.egg-info/top_level.txt