Metadata-Version: 1.1
Name: libplot
Version: 0.2.0
Summary: A library for creating beautiful plots.
Home-page: https://github.com/antonybholmes/libplot
Author: Antony B Holmes
Author-email: antony.b.holmes@gmail.com
License: UNKNOWN
Platform: UNKNOWN
Classifier: Programming Language :: Python :: 3
Classifier: License :: OSI Approved :: MIT License
Classifier: Operating System :: OS Independent
